blacksap.py
blacksap-1.8.0.dist-info/LICENSE
blacksap-1.8.0.dist-info/METADATA
blacksap-1.8.0.dist-info/WHEEL
blacksap-1.8.0.dist-info/entry_points.txt
blacksap-1.8.0.dist-info/top_level.txt
blacksap-1.8.0.dist-info/RECORD
