Metadata-Version: 2.1
Name: blacksap
Version: 1.8.0
Summary: Track torrent RSS feeds
Home-page: https://bitbucket.org/isaiah1112/blacksap
Author: Jesse Almanrode
Author-email: jesse@almanrode.com
License: GNU General Public License v3 or later (GPLv3+)
Platform: Linux
Platform: Darwin
Classifier: Development Status :: 5 - Production/Stable
Classifier: Intended Audience :: End Users/Desktop
Classifier: License :: OSI Approved :: GNU General Public License v3 or later (GPLv3+)
Classifier: Natural Language :: English
Classifier: Operating System :: MacOS :: MacOS X
Classifier: Operating System :: POSIX :: Linux
Classifier: Programming Language :: Python :: 3.7
Classifier: Programming Language :: Python :: 3.8
Classifier: Programming Language :: Python :: 3.9
Classifier: Programming Language :: Python :: 3.10
Classifier: Programming Language :: Python :: Implementation :: PyPy
Classifier: Topic :: Communications :: File Sharing
Classifier: Topic :: Utilities
Requires-Python: >3.7
License-File: LICENSE
Requires-Dist: click (>=8.1.3)
Requires-Dist: colorama (>=0.4.4)
Requires-Dist: feedparser (>=6.0.10)
Requires-Dist: PySocks (>=1.7.1)
Requires-Dist: requests (>=2.27.1)
